.git-blame-ignore-revs
.gitignore
.isort.cfg
.pre-commit-config.yaml
.readthedocs.yml
CONTRIBUTING.md
COPYING
COPYING.LESSER
DEPLOY.md
MAINTAINERS
MANIFEST.in
README.md
codecov.yml
manage.sh
pytest.ini
requirements.txt
setup.cfg
setup.py
test-requirements.txt
tox.ini
.github/FUNDING.yml
.github/dependabot.yml
.github/release-drafter.yml
.github/stale.yml
.github/workflows/ci.yml
.github/workflows/pypi-release.yml
PyGithub_Proxy_Dias_2000.egg-info/PKG-INFO
PyGithub_Proxy_Dias_2000.egg-info/SOURCES.txt
PyGithub_Proxy_Dias_2000.egg-info/dependency_links.txt
PyGithub_Proxy_Dias_2000.egg-info/requires.txt
PyGithub_Proxy_Dias_2000.egg-info/top_level.txt
doc/.gitignore
doc/Design.md
doc/changes.rst
doc/conf.py
doc/examples.rst
doc/github.rst
doc/index.rst
doc/introduction.rst
doc/reference.rst
doc/utilities.rst
doc/examples/Branch.rst
doc/examples/Commit.rst
doc/examples/Issue.rst
doc/examples/MainClass.rst
doc/examples/Milestone.rst
doc/examples/PullRequest.rst
doc/examples/Repository.rst
doc/examples/Webhook.rst
doc/github_objects/.gitignore
github/AccessToken.py
github/AccessToken.pyi
github/AppAuthentication.py
github/AppAuthentication.pyi
github/ApplicationOAuth.py
github/ApplicationOAuth.pyi
github/Artifact.py
github/Artifact.pyi
github/AuthenticatedUser.py
github/AuthenticatedUser.pyi
github/Authorization.py
github/Authorization.pyi
github/AuthorizationApplication.py
github/AuthorizationApplication.pyi
github/Autolink.py
github/Autolink.pyi
github/Branch.py
github/Branch.pyi
github/BranchProtection.py
github/BranchProtection.pyi
github/CheckRun.py
github/CheckRun.pyi
github/CheckRunAnnotation.py
github/CheckRunAnnotation.pyi
github/CheckRunOutput.py
github/CheckRunOutput.pyi
github/CheckSuite.py
github/CheckSuite.pyi
github/Clones.py
github/Clones.pyi
github/CodeScanAlert.py
github/CodeScanAlert.pyi
github/CodeScanAlertInstance.py
github/CodeScanAlertInstance.pyi
github/CodeScanAlertInstanceLocation.py
github/CodeScanAlertInstanceLocation.pyi
github/CodeScanRule.py
github/CodeScanRule.pyi
github/CodeScanTool.py
github/CodeScanTool.pyi
github/Commit.py
github/Commit.pyi
github/CommitCombinedStatus.py
github/CommitCombinedStatus.pyi
github/CommitComment.py
github/CommitComment.pyi
