Metadata-Version: 2.1
Name: PyGithub-Proxy-Dias-2000
Version: 0.0.1
Summary: Use the full Github API v3
Home-page: https://github.com/Mercurial5/PyGithub
Author: Dias
Author-email: dias.nespayev@gmail.com
Project-URL: Documentation, http://pygithub.readthedocs.io/en/latest/
Project-URL: Source, https://github.com/pygithub/pygithub
Project-URL: Tracker, https://github.com/pygithub/pygithub/issues
Classifier: Development Status :: 5 - Production/Stable
Classifier: Environment :: Web Environment
Classifier: Intended Audience :: Developers
Classifier: License :: OSI Approved :: GNU Library or Lesser General Public License (LGPL)
Classifier: Operating System :: OS Independent
Classifier: Programming Language :: Python
Classifier: Programming Language :: Python :: 3
Classifier: Programming Language :: Python :: 3.7
Classifier: Programming Language :: Python :: 3.8
Classifier: Programming Language :: Python :: 3.9
Classifier: Programming Language :: Python :: 3.10
Classifier: Programming Language :: Python :: 3.11
Classifier: Topic :: Software Development
Requires-Python: >=3.7
Provides-Extra: integrations
